mdslaremote/__init__.py
mdslaremote/mda.py
mdslaremote/impl/Call.py
mdslaremote/impl/Common.py
mdslaremote/impl/ConnectionSet.py
mdslaremote/impl/Group.py
mdslaremote/impl/Mdsla.py
mdslaremote/impl/Node.py
mdslaremote/impl/Result.py
mdslaremote/impl/TaskList.py
mdslaremote/impl/Test.py
mdslaremote/impl/__init__.py
mdslaremote-1.0.17.dist-info/LICENSE
mdslaremote-1.0.17.dist-info/METADATA
mdslaremote-1.0.17.dist-info/WHEEL
mdslaremote-1.0.17.dist-info/top_level.txt
mdslaremote-1.0.17.dist-info/RECORD
