Metadata-Version: 2.1
Name: mdslaremote
Version: 1.0.17
Summary: Python API for Opale Systems MultiDSLA System
Home-page: http://www.opalesystems.com
Author: Opale Systems
Author-email: support@opalesystems.com
License: MIT
Classifier: Programming Language :: Python :: 3
Classifier: License :: OSI Approved :: MIT License
Classifier: Operating System :: OS Independent
License-File: LICENSE
